{
  "event_id": "mock_fixture_web",
  "ts": "2026-04-17T12:00:00.000+08:00",
  "animal": {
    "animal_id": "dog_001",
    "species": "dog",
    "name": "MockDog",
    "breed": "mix",
    "sex": "unknown",
    "age_months": 24,
    "weight_kg": 12.5
  },
  "device": {
    "device_id": "web_mock_device_01",
    "firmware": "1.0.0-mock",
    "sampling_hz": { "accel": 50, "temperature": 1, "vitals": 1 }
  },
  "window": {
    "start_ts": "2026-04-17T11:59:40.000+08:00",
    "end_ts": "2026-04-17T12:00:00.000+08:00",
    "timezone": "+08:00"
  },
  "context": {
    "notes": "web fixture for n8n ingest",
    "tags": ["mock", "web", "fixture"],
    "location": { "lat": 31.23, "lng": 121.47, "accuracy_m": 10 }
  },
  "signals": {
    "accel": {
      "samples": [
        {"t_ms": 0, "x": 0.1, "y": 0.2, "z": 9.7},
        {"t_ms": 100, "x": 0.12, "y": 0.18, "z": 9.75},
        {"t_ms": 200, "x": 0.09, "y": 0.21, "z": 9.72},
        {"t_ms": 300, "x": 0.11, "y": 0.19, "z": 9.78},
        {"t_ms": 400, "x": 0.1, "y": 0.2, "z": 9.76},
        {"t_ms": 500, "x": 0.08, "y": 0.22, "z": 9.74},
        {"t_ms": 600, "x": 0.13, "y": 0.17, "z": 9.79},
        {"t_ms": 700, "x": 0.1, "y": 0.2, "z": 9.77},
        {"t_ms": 800, "x": 0.11, "y": 0.21, "z": 9.73},
        {"t_ms": 900, "x": 0.09, "y": 0.19, "z": 9.8},
        {"t_ms": 1000, "x": 0.12, "y": 0.18, "z": 9.76},
        {"t_ms": 1100, "x": 0.1, "y": 0.2, "z": 9.75},
        {"t_ms": 1200, "x": 0.11, "y": 0.22, "z": 9.78},
        {"t_ms": 1300, "x": 0.08, "y": 0.19, "z": 9.74},
        {"t_ms": 1400, "x": 0.1, "y": 0.21, "z": 9.77}
      ]
    },
    "vitals": {
      "samples": [
        {"t_s": 0, "hr": 92, "rr": 18},
        {"t_s": 1, "hr": 93, "rr": 19},
        {"t_s": 2, "hr": 91, "rr": 18},
        {"t_s": 3, "hr": 94, "rr": 20},
        {"t_s": 4, "hr": 92, "rr": 18},
        {"t_s": 5, "hr": 95, "rr": 19},
        {"t_s": 6, "hr": 93, "rr": 18},
        {"t_s": 7, "hr": 91, "rr": 20},
        {"t_s": 8, "hr": 92, "rr": 18},
        {"t_s": 9, "hr": 94, "rr": 19},
        {"t_s": 10, "hr": 93, "rr": 18},
        {"t_s": 11, "hr": 92, "rr": 20},
        {"t_s": 12, "hr": 96, "rr": 19},
        {"t_s": 13, "hr": 93, "rr": 18},
        {"t_s": 14, "hr": 91, "rr": 18}
      ]
    },
    "temperature": {
      "samples": [
        {"t_s": 0, "value": 38.2},
        {"t_s": 1, "value": 38.21},
        {"t_s": 2, "value": 38.19},
        {"t_s": 3, "value": 38.22},
        {"t_s": 4, "value": 38.2},
        {"t_s": 5, "value": 38.23},
        {"t_s": 6, "value": 38.18},
        {"t_s": 7, "value": 38.21},
        {"t_s": 8, "value": 38.2},
        {"t_s": 9, "value": 38.24},
        {"t_s": 10, "value": 38.19},
        {"t_s": 11, "value": 38.22},
        {"t_s": 12, "value": 38.2},
        {"t_s": 13, "value": 38.21},
        {"t_s": 14, "value": 38.2}
      ]
    }
  }
}
